[
  {
    "trunk_angle": 25.234228232028915,
    "nsar": null,
    "theta_u": null,
    "theta_d": null,
    "fall_detected": false
  },
  {
    "trunk_angle": 25.483187274241548,
    "nsar": null,
    "theta_u": null,
    "theta_d": null,
    "fall_detected": false
  },
  {
    "trunk_angle": 25.73160689012951,
    "nsar": null,
    "theta_u": null,
    "theta_d": null,
    "fall_detected": false
  },
  {
    "trunk_angle": 25.775676856116323,
    "nsar": null,
    "theta_u": null,
    "theta_d": null,
    "fall_detected": false
  },
  {
    "trunk_angle": 25.806341363502547,
    "nsar": null,
    "theta_u": null,
    "theta_d": null,
    "fall_detected": false
  },
  {
    "trunk_angle": 25.770459929625673,
    "nsar": null,
    "theta_u": null,
    "theta_d": null,
    "fall_detected": false
  },
  {
    "trunk_angle": 25.840293101162167,
    "nsar": null,
    "theta_u": null,
    "theta_d": null,
    "fall_detected": false
  },
  {
    "trunk_angle": 25.927399153845467,
    "nsar": null,
    "theta_u": null,
    "theta_d": null,
    "fall_detected": false
  },
  {
    "trunk_angle": 26.089101992213987,
    "nsar": null,
    "theta_u": null,
    "theta_d": null,
    "fall_detected": false
  },
  {
    "trunk_angle": 26.36211531027338,
    "nsar": null,
    "theta_u": null,
    "theta_d": null,
    "fall_detected": false
  },
  {
    "trunk_angle": 26.771691290627217,
    "nsar": null,
    "theta_u": null,
    "theta_d": null,
    "fall_detected": false
  },
  {
    "trunk_angle": 27.30463864039705,
    "nsar": null,
    "theta_u": null,
    "theta_d": null,
    "fall_detected": false
  },
  {
    "trunk_angle": 27.90058355012591,
    "nsar": null,
    "theta_u": null,
    "theta_d": null,
    "fall_detected": false
  },
  {
    "trunk_angle": 28.550253443838482,
    "nsar": null,
    "theta_u": null,
    "theta_d": null,
    "fall_detected": false
  },
  {
    "trunk_angle": 29.059512236819174,
    "nsar": null,
    "theta_u": null,
    "theta_d": null,
    "fall_detected": false
  },
  {
    "trunk_angle": 29.434135760736474,
    "nsar": null,
    "theta_u": null,
    "theta_d": null,
    "fall_detected": false
  },
  {
    "trunk_angle": 29.885862515796237,
    "nsar": null,
    "theta_u": null,
    "theta_d": null,
    "fall_detected": false
  },
  {
    "trunk_angle": 30.23749186526808,
    "nsar": null,
    "theta_u": null,
    "theta_d": null,
    "fall_detected": false
  },
  {
    "trunk_angle": 30.384689918130405,
    "nsar": null,
    "theta_u": null,
    "theta_d": null,
    "fall_detected": false
  },
  {
    "trunk_angle": 30.402763852779174,
    "nsar": null,
    "theta_u": null,
    "theta_d": null,
    "fall_detected": false
  },
  {
    "trunk_angle": 30.509242106856323,
    "nsar": null,
    "theta_u": null,
    "theta_d": null,
    "fall_detected": false
  },
  {
    "trunk_angle": 30.615225347879516,
    "nsar": null,
    "theta_u": null,
    "theta_d": null,
    "fall_detected": false
  },
  {
    "trunk_angle": 30.636362669151282,
    "nsar": null,
    "theta_u": null,
    "theta_d": null,
    "fall_detected": false
  },
  {
    "trunk_angle": 30.93312714623387,
    "nsar": null,
    "theta_u": null,
    "theta_d": null,
    "fall_detected": false
  },
  {
    "trunk_angle": 31.095283287407202,
    "nsar": null,
    "theta_u": null,
    "theta_d": null,
    "fall_detected": false
  },
  {
    "trunk_angle": 31.18621795848641,
    "nsar": null,
    "theta_u": null,
    "theta_d": null,
    "fall_detected": false
  },
  {
    "trunk_angle": 31.273708957060993,
    "nsar": null,
    "theta_u": null,
    "theta_d": null,
    "fall_detected": false
  },
  {
    "trunk_angle": 31.44133240295986,
    "nsar": null,
    "theta_u": null,
    "theta_d": null,
    "fall_detected": false
  },
  {
    "trunk_angle": 31.338541782163116,
    "nsar": null,
    "theta_u": null,
    "theta_d": null,
    "fall_detected": false
  },
  {
    "trunk_angle": 31.21945959748044,
    "nsar": null,
    "theta_u": null,
    "theta_d": null,
    "fall_detected": false
  },
  {
    "trunk_angle": 31.248118431606844,
    "nsar": null,
    "theta_u": null,
    "theta_d": null,
    "fall_detected": false
  },
  {
    "trunk_angle": 31.12831501370127,
    "nsar": null,
    "theta_u": null,
    "theta_d": null,
    "fall_detected": false
  },
  {
    "trunk_angle": 31.062860446828434,
    "nsar": null,
    "theta_u": null,
    "theta_d": null,
    "fall_detected": false
  },
  {
    "trunk_angle": 31.04730540881555,
    "nsar": null,
    "theta_u": null,
    "theta_d": null,
    "fall_detected": false
  },
  {
    "trunk_angle": 31.065371556220985,
    "nsar": null,
    "theta_u": null,
    "theta_d": null,
    "fall_detected": false
  },
  {
    "trunk_angle": 31.17131059601951,
    "nsar": null,
    "theta_u": null,
    "theta_d": null,
    "fall_detected": false
  },
  {
    "trunk_angle": 31.34351550392068,
    "nsar": null,
    "theta_u": null,
    "theta_d": null,
    "fall_detected": false
  },
  {
    "trunk_angle": 31.694713621857648,
    "nsar": null,
    "theta_u": null,
    "theta_d": null,
    "fall_detected": false
  },
  {
    "trunk_angle": 32.103575248312936,
    "nsar": null,
    "theta_u": null,
    "theta_d": null,
    "fall_detected": false
  },
  {
    "trunk_angle": 32.48714915517458,
    "nsar": null,
    "theta_u": null,
    "theta_d": null,
    "fall_detected": false
  },
  {
    "trunk_angle": 32.87781447889788,
    "nsar": null,
    "theta_u": null,
    "theta_d": null,
    "fall_detected": false
  },
  {
    "trunk_angle": 33.18661306625214,
    "nsar": null,
    "theta_u": null,
    "theta_d": null,
    "fall_detected": false
  },
  {
    "trunk_angle": 33.25672678116052,
    "nsar": null,
    "theta_u": null,
    "theta_d": null,
    "fall_detected": false
  },
  {
    "trunk_angle": 33.3410702359071,
    "nsar": null,
    "theta_u": null,
    "theta_d": null,
    "fall_detected": false
  },
  {
    "trunk_angle": 33.35594789815678,
    "nsar": null,
    "theta_u": null,
    "theta_d": null,
    "fall_detected": false
  },
  {
    "trunk_angle": 33.25409824037326,
    "nsar": null,
    "theta_u": null,
    "theta_d": null,
    "fall_detected": false
  },
  {
    "trunk_angle": 33.01274444308977,
    "nsar": null,
    "theta_u": null,
    "theta_d": null,
    "fall_detected": false
  },
  {
    "trunk_angle": 32.791959858308495,
    "nsar": null,
    "theta_u": null,
    "theta_d": null,
    "fall_detected": false
  },
  {
    "trunk_angle": 32.58647350880447,
    "nsar": null,
    "theta_u": null,
    "theta_d": null,
    "fall_detected": false
  },
  {
    "trunk_angle": 32.40364261872702,
    "nsar": null,
    "theta_u": null,
    "theta_d": null,
    "fall_detected": false
  },
  {
    "trunk_angle": 32.52364024884639,
    "nsar": null,
    "theta_u": null,
    "theta_d": null,
    "fall_detected": false
  },
  {
    "trunk_angle": 32.53069811037141,
    "nsar": null,
    "theta_u": null,
    "theta_d": null,
    "fall_detected": false
  },
  {
    "trunk_angle": 32.700156967623435,
    "nsar": null,
    "theta_u": null,
    "theta_d": null,
    "fall_detected": false
  },
  {
    "trunk_angle": 32.892845614741454,
    "nsar": null,
    "theta_u": null,
    "theta_d": null,
    "fall_detected": false
  },
  {
    "trunk_angle": 33.224265044625696,
    "nsar": null,
    "theta_u": null,
    "theta_d": null,
    "fall_detected": false
  },
  {
    "trunk_angle": 33.374653204059854,
    "nsar": null,
    "theta_u": null,
    "theta_d": null,
    "fall_detected": false
  },
  {
    "trunk_angle": 33.557917660200395,
    "nsar": null,
    "theta_u": null,
    "theta_d": null,
    "fall_detected": false
  },
  {
    "trunk_angle": 33.684741900045374,
    "nsar": null,
    "theta_u": null,
    "theta_d": null,
    "fall_detected": false
  },
  {
    "trunk_angle": 33.72226932127669,
    "nsar": null,
    "theta_u": null,
    "theta_d": null,
    "fall_detected": false
  },
  {
    "trunk_angle": 33.79316967485016,
    "nsar": null,
    "theta_u": null,
    "theta_d": null,
    "fall_detected": false
  },
  {
    "trunk_angle": 33.865081701605945,
    "nsar": null,
    "theta_u": null,
    "theta_d": null,
    "fall_detected": true
  },
  {
    "trunk_angle": 33.838132687318776,
    "nsar": null,
    "theta_u": null,
    "theta_d": null,
    "fall_detected": true
  },
  {
    "trunk_angle": 33.65541056876425,
    "nsar": null,
    "theta_u": null,
    "theta_d": null,
    "fall_detected": false
  },
  {
    "trunk_angle": 33.600438966163125,
    "nsar": null,
    "theta_u": null,
    "theta_d": null,
    "fall_detected": false
  },
  {
    "trunk_angle": 33.25558715247881,
    "nsar": null,
    "theta_u": null,
    "theta_d": null,
    "fall_detected": false
  },
  {
    "trunk_angle": 32.85633184781245,
    "nsar": null,
    "theta_u": null,
    "theta_d": null,
    "fall_detected": false
  },
  {
    "trunk_angle": 32.551438207228465,
    "nsar": null,
    "theta_u": null,
    "theta_d": null,
    "fall_detected": false
  },
  {
    "trunk_angle": 32.13538434959701,
    "nsar": null,
    "theta_u": null,
    "theta_d": null,
    "fall_detected": false
  },
  {
    "trunk_angle": 31.73746026077212,
    "nsar": null,
    "theta_u": null,
    "theta_d": null,
    "fall_detected": false
  },
  {
    "trunk_angle": 31.313774655868993,
    "nsar": null,
    "theta_u": null,
    "theta_d": null,
    "fall_detected": false
  },
  {
    "trunk_angle": 30.941738311719067,
    "nsar": null,
    "theta_u": null,
    "theta_d": null,
    "fall_detected": false
  },
  {
    "trunk_angle": 30.65591895711442,
    "nsar": null,
    "theta_u": null,
    "theta_d": null,
    "fall_detected": false
  },
  {
    "trunk_angle": 30.635649016470037,
    "nsar": null,
    "theta_u": null,
    "theta_d": null,
    "fall_detected": false
  },
  {
    "trunk_angle": 30.838393564773163,
    "nsar": null,
    "theta_u": null,
    "theta_d": null,
    "fall_detected": false
  },
  {
    "trunk_angle": 30.847048275010845,
    "nsar": null,
    "theta_u": null,
    "theta_d": null,
    "fall_detected": false
  },
  {
    "trunk_angle": 31.04553933255009,
    "nsar": null,
    "theta_u": null,
    "theta_d": null,
    "fall_detected": false
  },
  {
    "trunk_angle": 31.35487929093793,
    "nsar": null,
    "theta_u": null,
    "theta_d": null,
    "fall_detected": false
  },
  {
    "trunk_angle": 31.712750153193255,
    "nsar": null,
    "theta_u": null,
    "theta_d": null,
    "fall_detected": false
  },
  {
    "trunk_angle": 31.96937312992398,
    "nsar": null,
    "theta_u": null,
    "theta_d": null,
    "fall_detected": false
  },
  {
    "trunk_angle": 32.113973046054156,
    "nsar": null,
    "theta_u": null,
    "theta_d": null,
    "fall_detected": false
  },
  {
    "trunk_angle": 32.19381484511337,
    "nsar": null,
    "theta_u": null,
    "theta_d": null,
    "fall_detected": false
  },
  {
    "trunk_angle": 32.20212135542952,
    "nsar": null,
    "theta_u": null,
    "theta_d": null,
    "fall_detected": false
  },
  {
    "trunk_angle": 32.303758500684154,
    "nsar": null,
    "theta_u": null,
    "theta_d": null,
    "fall_detected": false
  },
  {
    "trunk_angle": 32.29662702985042,
    "nsar": null,
    "theta_u": null,
    "theta_d": null,
    "fall_detected": false
  },
  {
    "trunk_angle": 32.25980339370217,
    "nsar": null,
    "theta_u": null,
    "theta_d": null,
    "fall_detected": false
  },
  {
    "trunk_angle": 32.18364396962938,
    "nsar": null,
    "theta_u": null,
    "theta_d": null,
    "fall_detected": false
  },
  {
    "trunk_angle": 32.24183871378476,
    "nsar": null,
    "theta_u": null,
    "theta_d": null,
    "fall_detected": false
  },
  {
    "trunk_angle": 32.394183762185776,
    "nsar": null,
    "theta_u": null,
    "theta_d": null,
    "fall_detected": false
  },
  {
    "trunk_angle": 32.36508377089948,
    "nsar": null,
    "theta_u": null,
    "theta_d": null,
    "fall_detected": false
  },
  {
    "trunk_angle": 32.45740308735914,
    "nsar": null,
    "theta_u": null,
    "theta_d": null,
    "fall_detected": false
  },
  {
    "trunk_angle": 32.52773082781948,
    "nsar": null,
    "theta_u": null,
    "theta_d": null,
    "fall_detected": false
  },
  {
    "trunk_angle": 32.666908311015604,
    "nsar": null,
    "theta_u": null,
    "theta_d": null,
    "fall_detected": false
  },
  {
    "trunk_angle": 32.58925007853139,
    "nsar": null,
    "theta_u": null,
    "theta_d": null,
    "fall_detected": false
  },
  {
    "trunk_angle": 32.50238814740209,
    "nsar": null,
    "theta_u": null,
    "theta_d": null,
    "fall_detected": false
  },
  {
    "trunk_angle": 32.4794948236865,
    "nsar": null,
    "theta_u": null,
    "theta_d": null,
    "fall_detected": false
  },
  {
    "trunk_angle": 32.607940930690035,
    "nsar": null,
    "theta_u": null,
    "theta_d": null,
    "fall_detected": false
  },
  {
    "trunk_angle": 33.07179928279805,
    "nsar": null,
    "theta_u": null,
    "theta_d": null,
    "fall_detected": false
  },
  {
    "trunk_angle": 33.26923736780553,
    "nsar": null,
    "theta_u": null,
    "theta_d": null,
    "fall_detected": false
  },
  {
    "trunk_angle": 33.54173335900704,
    "nsar": null,
    "theta_u": null,
    "theta_d": null,
    "fall_detected": false
  },
  {
    "trunk_angle": 33.94063794077995,
    "nsar": null,
    "theta_u": null,
    "theta_d": null,
    "fall_detected": true
  },
  {
    "trunk_angle": 34.33953130587824,
    "nsar": null,
    "theta_u": null,
    "theta_d": null,
    "fall_detected": true
  },
  {
    "trunk_angle": 34.90742269862018,
    "nsar": null,
    "theta_u": null,
    "theta_d": null,
    "fall_detected": true
  },
  {
    "trunk_angle": 35.43891463810851,
    "nsar": null,
    "theta_u": null,
    "theta_d": null,
    "fall_detected": true
  },
  {
    "trunk_angle": 35.591293719404575,
    "nsar": null,
    "theta_u": null,
    "theta_d": null,
    "fall_detected": true
  },
  {
    "trunk_angle": 35.65941368505321,
    "nsar": null,
    "theta_u": null,
    "theta_d": null,
    "fall_detected": true
  },
  {
    "trunk_angle": 35.734938160104925,
    "nsar": null,
    "theta_u": null,
    "theta_d": null,
    "fall_detected": true
  },
  {
    "trunk_angle": 36.13850576960212,
    "nsar": null,
    "theta_u": null,
    "theta_d": null,
    "fall_detected": true
  },
  {
    "trunk_angle": null,
    "nsar": null,
    "theta_u": null,
    "theta_d": null,
    "fall_detected": false
  },
  {
    "trunk_angle": null,
    "nsar": null,
    "theta_u": null,
    "theta_d": null,
    "fall_detected": false
  },
  {
    "trunk_angle": 36.329190166425406,
    "nsar": null,
    "theta_u": null,
    "theta_d": null,
    "fall_detected": true
  },
  {
    "trunk_angle": null,
    "nsar": null,
    "theta_u": null,
    "theta_d": null,
    "fall_detected": false
  },
  {
    "trunk_angle": 35.7384603944322,
    "nsar": null,
    "theta_u": null,
    "theta_d": null,
    "fall_detected": true
  },
  {
    "trunk_angle": null,
    "nsar": null,
    "theta_u": null,
    "theta_d": null,
    "fall_detected": false
  },
  {
    "trunk_angle": 34.513112921171015,
    "nsar": null,
    "theta_u": null,
    "theta_d": null,
    "fall_detected": true
  },
  {
    "trunk_angle": 34.293232325339524,
    "nsar": null,
    "theta_u": null,
    "theta_d": null,
    "fall_detected": true
  },
  {
    "trunk_angle": 33.94404280051194,
    "nsar": null,
    "theta_u": null,
    "theta_d": null,
    "fall_detected": true
  },
  {
    "trunk_angle": 32.966617066808126,
    "nsar": null,
    "theta_u": null,
    "theta_d": null,
    "fall_detected": false
  },
  {
    "trunk_angle": 31.755680124776873,
    "nsar": null,
    "theta_u": null,
    "theta_d": null,
    "fall_detected": false
  },
  {
    "trunk_angle": null,
    "nsar": null,
    "theta_u": null,
    "theta_d": null,
    "fall_detected": false
  },
  {
    "trunk_angle": 29.45836822838815,
    "nsar": null,
    "theta_u": null,
    "theta_d": null,
    "fall_detected": false
  },
  {
    "trunk_angle": 26.809819915915337,
    "nsar": null,
    "theta_u": null,
    "theta_d": null,
    "fall_detected": false
  },
  {
    "trunk_angle": 24.805380676347664,
    "nsar": null,
    "theta_u": null,
    "theta_d": null,
    "fall_detected": false
  },
  {
    "trunk_angle": 23.24840639730967,
    "nsar": null,
    "theta_u": null,
    "theta_d": null,
    "fall_detected": false
  },
  {
    "trunk_angle": 20.544115479573023,
    "nsar": null,
    "theta_u": null,
    "theta_d": null,
    "fall_detected": false
  },
  {
    "trunk_angle": 17.80916518960438,
    "nsar": null,
    "theta_u": null,
    "theta_d": null,
    "fall_detected": false
  },
  {
    "trunk_angle": 15.609593390828469,
    "nsar": null,
    "theta_u": null,
    "theta_d": null,
    "fall_detected": false
  },
  {
    "trunk_angle": 13.7705943464534,
    "nsar": null,
    "theta_u": null,
    "theta_d": null,
    "fall_detected": false
  },
  {
    "trunk_angle": 12.524508027762481,
    "nsar": null,
    "theta_u": null,
    "theta_d": null,
    "fall_detected": false
  },
  {
    "trunk_angle": 11.538995272345788,
    "nsar": null,
    "theta_u": null,
    "theta_d": null,
    "fall_detected": false
  },
  {
    "trunk_angle": 10.836883808204579,
    "nsar": null,
    "theta_u": null,
    "theta_d": null,
    "fall_detected": false
  },
  {
    "trunk_angle": 10.156524783139442,
    "nsar": null,
    "theta_u": null,
    "theta_d": null,
    "fall_detected": false
  },
  {
    "trunk_angle": 9.52076735405233,
    "nsar": null,
    "theta_u": null,
    "theta_d": null,
    "fall_detected": false
  },
  {
    "trunk_angle": 9.39751913788078,
    "nsar": null,
    "theta_u": null,
    "theta_d": null,
    "fall_detected": false
  },
  {
    "trunk_angle": 9.387662215814803,
    "nsar": null,
    "theta_u": null,
    "theta_d": null,
    "fall_detected": false
  },
  {
    "trunk_angle": 9.52355649206328,
    "nsar": null,
    "theta_u": null,
    "theta_d": null,
    "fall_detected": false
  },
  {
    "trunk_angle": 9.55539608530257,
    "nsar": null,
    "theta_u": null,
    "theta_d": null,
    "fall_detected": false
  },
  {
    "trunk_angle": 9.869064589293604,
    "nsar": null,
    "theta_u": null,
    "theta_d": null,
    "fall_detected": false
  },
  {
    "trunk_angle": 10.58237985916871,
    "nsar": null,
    "theta_u": null,
    "theta_d": null,
    "fall_detected": false
  },
  {
    "trunk_angle": 11.434500914245168,
    "nsar": null,
    "theta_u": null,
    "theta_d": null,
    "fall_detected": false
  },
  {
    "trunk_angle": 12.577833793238375,
    "nsar": null,
    "theta_u": null,
    "theta_d": null,
    "fall_detected": false
  },
  {
    "trunk_angle": 13.65195237046819,
    "nsar": null,
    "theta_u": null,
    "theta_d": null,
    "fall_detected": false
  },
  {
    "trunk_angle": 14.539498702020339,
    "nsar": null,
    "theta_u": null,
    "theta_d": null,
    "fall_detected": false
  },
  {
    "trunk_angle": 14.546132559038426,
    "nsar": null,
    "theta_u": null,
    "theta_d": null,
    "fall_detected": false
  },
  {
    "trunk_angle": 14.605751617481834,
    "nsar": null,
    "theta_u": null,
    "theta_d": null,
    "fall_detected": false
  },
  {
    "trunk_angle": 14.325802403675693,
    "nsar": null,
    "theta_u": null,
    "theta_d": null,
    "fall_detected": false
  },
  {
    "trunk_angle": 13.78449367400952,
    "nsar": null,
    "theta_u": null,
    "theta_d": null,
    "fall_detected": false
  },
  {
    "trunk_angle": 12.733685890170683,
    "nsar": null,
    "theta_u": null,
    "theta_d": null,
    "fall_detected": false
  },
  {
    "trunk_angle": 11.471182148422589,
    "nsar": null,
    "theta_u": null,
    "theta_d": null,
    "fall_detected": false
  },
  {
    "trunk_angle": 9.81578141296651,
    "nsar": null,
    "theta_u": null,
    "theta_d": null,
    "fall_detected": false
  },
  {
    "trunk_angle": 8.094415035882802,
    "nsar": null,
    "theta_u": null,
    "theta_d": null,
    "fall_detected": false
  },
  {
    "trunk_angle": 7.012657633404576,
    "nsar": null,
    "theta_u": null,
    "theta_d": null,
    "fall_detected": false
  },
  {
    "trunk_angle": 6.162377863642154,
    "nsar": null,
    "theta_u": null,
    "theta_d": null,
    "fall_detected": false
  },
  {
    "trunk_angle": 5.79473366111974,
    "nsar": null,
    "theta_u": null,
    "theta_d": null,
    "fall_detected": false
  },
  {
    "trunk_angle": 5.553282203301316,
    "nsar": null,
    "theta_u": null,
    "theta_d": null,
    "fall_detected": false
  },
  {
    "trunk_angle": 5.54101122581897,
    "nsar": null,
    "theta_u": null,
    "theta_d": null,
    "fall_detected": false
  },
  {
    "trunk_angle": 6.687589945502848,
    "nsar": null,
    "theta_u": null,
    "theta_d": null,
    "fall_detected": false
  },
  {
    "trunk_angle": 7.866730593542927,
    "nsar": null,
    "theta_u": null,
    "theta_d": null,
    "fall_detected": false
  },
  {
    "trunk_angle": 8.693295676206171,
    "nsar": null,
    "theta_u": null,
    "theta_d": null,
    "fall_detected": false
  },
  {
    "trunk_angle": 9.86270623706904,
    "nsar": null,
    "theta_u": null,
    "theta_d": null,
    "fall_detected": false
  },
  {
    "trunk_angle": 10.56544117433009,
    "nsar": null,
    "theta_u": null,
    "theta_d": null,
    "fall_detected": false
  },
  {
    "trunk_angle": 9.831667062080722,
    "nsar": null,
    "theta_u": null,
    "theta_d": null,
    "fall_detected": false
  },
  {
    "trunk_angle": 8.83825457051151,
    "nsar": null,
    "theta_u": null,
    "theta_d": null,
    "fall_detected": false
  },
  {
    "trunk_angle": 8.177982371069474,
    "nsar": null,
    "theta_u": null,
    "theta_d": null,
    "fall_detected": false
  },
  {
    "trunk_angle": 6.156300709584542,
    "nsar": null,
    "theta_u": null,
    "theta_d": null,
    "fall_detected": false
  },
  {
    "trunk_angle": 4.965223941708169,
    "nsar": null,
    "theta_u": null,
    "theta_d": null,
    "fall_detected": false
  },
  {
    "trunk_angle": 4.453207725437315,
    "nsar": null,
    "theta_u": null,
    "theta_d": null,
    "fall_detected": false
  },
  {
    "trunk_angle": 4.258106036000426,
    "nsar": null,
    "theta_u": null,
    "theta_d": null,
    "fall_detected": false
  },
  {
    "trunk_angle": 4.55683296894884,
    "nsar": null,
    "theta_u": null,
    "theta_d": null,
    "fall_detected": false
  },
  {
    "trunk_angle": 6.074457584859996,
    "nsar": null,
    "theta_u": null,
    "theta_d": null,
    "fall_detected": false
  },
  {
    "trunk_angle": 7.817303961831971,
    "nsar": null,
    "theta_u": null,
    "theta_d": null,
    "fall_detected": false
  },
  {
    "trunk_angle": 10.70616495026,
    "nsar": null,
    "theta_u": null,
    "theta_d": null,
    "fall_detected": false
  },
  {
    "trunk_angle": 13.902769261407103,
    "nsar": null,
    "theta_u": null,
    "theta_d": null,
    "fall_detected": false
  },
  {
    "trunk_angle": 16.896001680159063,
    "nsar": null,
    "theta_u": null,
    "theta_d": null,
    "fall_detected": false
  },
  {
    "trunk_angle": 20.28229910020083,
    "nsar": null,
    "theta_u": null,
    "theta_d": null,
    "fall_detected": false
  },
  {
    "trunk_angle": 23.350655807468073,
    "nsar": null,
    "theta_u": null,
    "theta_d": null,
    "fall_detected": false
  },
  {
    "trunk_angle": 26.68962883793582,
    "nsar": null,
    "theta_u": null,
    "theta_d": null,
    "fall_detected": false
  },
  {
    "trunk_angle": 30.32324227098683,
    "nsar": null,
    "theta_u": null,
    "theta_d": null,
    "fall_detected": false
  },
  {
    "trunk_angle": 33.625663082721736,
    "nsar": null,
    "theta_u": null,
    "theta_d": null,
    "fall_detected": false
  },
  {
    "trunk_angle": 35.98024349278782,
    "nsar": null,
    "theta_u": null,
    "theta_d": null,
    "fall_detected": true
  },
  {
    "trunk_angle": 38.5493362037601,
    "nsar": null,
    "theta_u": null,
    "theta_d": null,
    "fall_detected": true
  },
  {
    "trunk_angle": 41.369031248165236,
    "nsar": null,
    "theta_u": null,
    "theta_d": null,
    "fall_detected": true
  },
  {
    "trunk_angle": 43.87898747399405,
    "nsar": null,
    "theta_u": null,
    "theta_d": null,
    "fall_detected": true
  },
  {
    "trunk_angle": 46.573740002975455,
    "nsar": null,
    "theta_u": null,
    "theta_d": null,
    "fall_detected": true
  },
  {
    "trunk_angle": 49.05098499466051,
    "nsar": null,
    "theta_u": null,
    "theta_d": null,
    "fall_detected": true
  },
  {
    "trunk_angle": 51.18447393631796,
    "nsar": 0.16352201257861634,
    "theta_u": 146.1038334366361,
    "theta_d": 176.28471089457128,
    "fall_detected": true
  },
  {
    "trunk_angle": 53.271602446762614,
    "nsar": 0.15771037337791577,
    "theta_u": 146.94417718844633,
    "theta_d": 175.6012946450045,
    "fall_detected": true
  },
  {
    "trunk_angle": 54.79086085021695,
    "nsar": 0.15126184221001512,
    "theta_u": 147.75753216087668,
    "theta_d": 174.21760767763598,
    "fall_detected": true
  },
  {
    "trunk_angle": 55.70201339847885,
    "nsar": 0.14760787234074116,
    "theta_u": 150.64224645720873,
    "theta_d": 175.76360520094116,
    "fall_detected": true
  },
  {
    "trunk_angle": 55.76277682092155,
    "nsar": 0.1447529645392596,
    "theta_u": 152.74467162505695,
    "theta_d": 170.99149625797486,
    "fall_detected": true
  },
  {
    "trunk_angle": 55.2716924307786,
    "nsar": null,
    "theta_u": null,
    "theta_d": null,
    "fall_detected": true
  },
  {
    "trunk_angle": 54.04112622958533,
    "nsar": 0.14643392206228623,
    "theta_u": 159.35300917502965,
    "theta_d": 171.75367918553152,
    "fall_detected": true
  },
  {
    "trunk_angle": 52.75114372262553,
    "nsar": 0.1480711813165461,
    "theta_u": 161.31264849478885,
    "theta_d": 171.99527114270714,
    "fall_detected": true
  },
  {
    "trunk_angle": 51.2997258902818,
    "nsar": 0.1496965118398973,
    "theta_u": 160.0835940061909,
    "theta_d": 171.60707481260752,
    "fall_detected": true
  },
  {
    "trunk_angle": 49.567587854677996,
    "nsar": 0.1480918767059264,
    "theta_u": 159.07549825507886,
    "theta_d": 177.13759477388822,
    "fall_detected": true
  },
  {
    "trunk_angle": 47.82507117353369,
    "nsar": 0.14820175715599673,
    "theta_u": 158.6293777306568,
    "theta_d": 172.87498365109818,
    "fall_detected": true
  },
  {
    "trunk_angle": 45.211840002658754,
    "nsar": 0.1502723568548186,
    "theta_u": 161.32329826780992,
    "theta_d": 174.6106882400266,
    "fall_detected": true
  },
  {
    "trunk_angle": 42.159039118971535,
    "nsar": 0.1555796712146962,
    "theta_u": 164.2679952148927,
    "theta_d": 176.18592516570973,
    "fall_detected": true
  },
  {
    "trunk_angle": 38.924796853683574,
    "nsar": 0.16876375081668626,
    "theta_u": 167.90524292298792,
    "theta_d": 170.9605171966449,
    "fall_detected": true
  },
  {
    "trunk_angle": 35.750019615580584,
    "nsar": 0.18484198297315058,
    "theta_u": 168.53046966713308,
    "theta_d": 163.44292862436336,
    "fall_detected": true
  },
  {
    "trunk_angle": 32.45677567452216,
    "nsar": 0.20570343146617803,
    "theta_u": 169.17698877379294,
    "theta_d": 171.869897645844,
    "fall_detected": false
  },
  {
    "trunk_angle": 29.286023709117924,
    "nsar": 0.22760460150834705,
    "theta_u": 168.1975657922165,
    "theta_d": 177.87890360333856,
    "fall_detected": false
  },
  {
    "trunk_angle": 26.810160718463656,
    "nsar": 0.23654676284776868,
    "theta_u": 160.78732818281438,
    "theta_d": 167.19573393471325,
    "fall_detected": false
  },
  {
    "trunk_angle": 24.76419435384873,
    "nsar": 0.23972676834831871,
    "theta_u": 156.467651439099,
    "theta_d": 153.434948822922,
    "fall_detected": false
  },
  {
    "trunk_angle": 24.33623149582683,
    "nsar": 0.24186594750930615,
    "theta_u": 148.33924890336343,
    "theta_d": 175.9143832200252,
    "fall_detected": false
  },
  {
    "trunk_angle": 24.633848609196072,
    "nsar": 0.23435884018876602,
    "theta_u": 142.27500495788928,
    "theta_d": 152.1027289690524,
    "fall_detected": false
  },
  {
    "trunk_angle": 25.491094229593852,
    "nsar": 0.22889833782254831,
    "theta_u": 138.73139699916047,
    "theta_d": 150.2551187030578,
    "fall_detected": false
  },
  {
    "trunk_angle": 27.02359920679403,
    "nsar": 0.1966298239184319,
    "theta_u": 133.069412558833,
    "theta_d": 158.1985905136482,
    "fall_detected": false
  },
  {
    "trunk_angle": 29.35358562540103,
    "nsar": 0.17205717434578233,
    "theta_u": 125.05942696688697,
    "theta_d": 137.91083782616775,
    "fall_detected": false
  },
  {
    "trunk_angle": 32.25090234992402,
    "nsar": 0.1530480919051675,
    "theta_u": 121.90810693565318,
    "theta_d": 137.41950921665634,
    "fall_detected": false
  },
  {
    "trunk_angle": 35.00087037212101,
    "nsar": 0.1530480919051675,
    "theta_u": 120.32360686255,
    "theta_d": 135.7440592028887,
    "fall_detected": true
  },
  {
    "trunk_angle": 37.54358772051471,
    "nsar": 0.15816812445636783,
    "theta_u": 120.96375653207352,
    "theta_d": 131.18592516570965,
    "fall_detected": true
  },
  {
    "trunk_angle": 39.53212775928766,
    "nsar": 0.1704465318960656,
    "theta_u": 122.10625595511783,
    "theta_d": 130.1354855622395,
    "fall_detected": true
  },
  {
    "trunk_angle": 41.39229499439247,
    "nsar": 0.18021346683905687,
    "theta_u": 120.65066795705286,
    "theta_d": 123.25436657471207,
    "fall_detected": true
  },
  {
    "trunk_angle": 43.1428820693319,
    "nsar": 0.18751336378168826,
    "theta_u": 121.55138494831347,
    "theta_d": 117.89727103094764,
    "fall_detected": true
  },
  {
    "trunk_angle": 44.130379673745864,
    "nsar": 0.20195444062247986,
    "theta_u": 120.37912601136834,
    "theta_d": 114.32557523912611,
    "fall_detected": true
  },
  {
    "trunk_angle": 44.20160747138743,
    "nsar": 0.20108031474835397,
    "theta_u": 120.8157057517292,
    "theta_d": 114.19320898728877,
    "fall_detected": true
  },
  {
    "trunk_angle": 43.83891532887203,
    "nsar": 0.2153674317947012,
    "theta_u": 120.96375653207352,
    "theta_d": 112.21759426951832,
    "fall_detected": true
  },
  {
    "trunk_angle": 43.62718493744336,
    "nsar": 0.249065063852989,
    "theta_u": 119.6237487511738,
    "theta_d": 109.98310652189998,
    "fall_detected": true
  },
  {
    "trunk_angle": 43.81896081251428,
    "nsar": 0.28530416721538,
    "theta_u": 116.98023071822286,
    "theta_d": 104.70830389968275,
    "fall_detected": true
  },
  {
    "trunk_angle": 44.00464847916474,
    "nsar": 0.32374260565381846,
    "theta_u": 116.98023071822286,
    "theta_d": 102.60015982608068,
    "fall_detected": true
  },
  {
    "trunk_angle": 44.18257729710984,
    "nsar": 0.3567870260221825,
    "theta_u": 114.59011716619602,
    "theta_d": 99.7824070318073,
    "fall_detected": true
  },
  {
    "trunk_angle": 44.2073590111966,
    "nsar": 0.402019962100189,
    "theta_u": 116.98023071822286,
    "theta_d": 100.53918372862823,
    "fall_detected": true
  },
  {
    "trunk_angle": 44.760862869612005,
    "nsar": 0.4746921060751499,
    "theta_u": 114.36245301531218,
    "theta_d": 100.75096699318806,
    "fall_detected": true
  },
  {
    "trunk_angle": 45.48238737657637,
    "nsar": 0.5055932225025821,
    "theta_u": 114.44395478041653,
    "theta_d": 99.9638041899072,
    "fall_detected": true
  },
  {
    "trunk_angle": 45.49613433875989,
    "nsar": 0.47437735064237097,
    "theta_u": 117.80145877993414,
    "theta_d": 98.9726266148964,
    "fall_detected": true
  },
  {
    "trunk_angle": null,
    "nsar": null,
    "theta_u": null,
    "theta_d": null,
    "fall_detected": false
  },
  {
    "trunk_angle": 44.54488973401689,
    "nsar": 0.4187158942946775,
    "theta_u": 118.61045966596521,
    "theta_d": 100.88552705465874,
    "fall_detected": true
  },
  {
    "trunk_angle": 43.10370075509218,
    "nsar": 0.38556733553636263,
    "theta_u": 120.80144597613682,
    "theta_d": 100.09750438407528,
    "fall_detected": true
  },
  {
    "trunk_angle": 42.0461699554638,
    "nsar": 0.3396609027878246,
    "theta_u": 119.14807184571305,
    "theta_d": 100.61965527615513,
    "fall_detected": true
  },
  {
    "trunk_angle": 40.83240740243781,
    "nsar": 0.3176828808098026,
    "theta_u": 120.61860540890939,
    "theta_d": 100.8230112262071,
    "fall_detected": true
  },
  {
    "trunk_angle": 40.07127872753568,
    "nsar": 0.2754820261089479,
    "theta_u": 116.99583839408663,
    "theta_d": 103.10920819815429,
    "fall_detected": true
  },
  {
    "trunk_angle": 39.15287151709208,
    "nsar": 0.22196895421352308,
    "theta_u": 117.84757825978818,
    "theta_d": 101.30993247402021,
    "fall_detected": true
  },
  {
    "trunk_angle": 38.350739429053405,
    "nsar": 0.2306038226345757,
    "theta_u": 118.30075576600639,
    "theta_d": 99.9638041899072,
    "fall_detected": true
  },
  {
    "trunk_angle": 37.71588692323664,
    "nsar": 0.2503683306244832,
    "theta_u": 116.99583839408663,
    "theta_d": 94.83041995828994,
    "fall_detected": true
  },
  {
    "trunk_angle": 37.7359421472035,
    "nsar": 0.25416976175149575,
    "theta_u": 116.1468412355809,
    "theta_d": 94.1446237411043,
    "fall_detected": true
  },
  {
    "trunk_angle": 37.834112319179454,
    "nsar": 0.2340986235401136,
    "theta_u": 113.57470620191262,
    "theta_d": 94.57392125990086,
    "fall_detected": true
  },
  {
    "trunk_angle": 37.2996229379406,
    "nsar": 0.27596465224824757,
    "theta_u": 116.09542415738835,
    "theta_d": 90.0,
    "fall_detected": true
  },
  {
    "trunk_angle": 36.854456695672575,
    "nsar": 0.3323556296918566,
    "theta_u": 117.5528115767178,
    "theta_d": 87.17287542183873,
    "fall_detected": true
  },
  {
    "trunk_angle": 36.17428389117441,
    "nsar": 0.3809667408029677,
    "theta_u": 115.08359400619092,
    "theta_d": 88.00212014352333,
    "fall_detected": true
  },
  {
    "trunk_angle": 35.44068546717803,
    "nsar": 0.4237474894660693,
    "theta_u": 116.09542415738835,
    "theta_d": 88.66778014613037,
    "fall_detected": true
  },
  {
    "trunk_angle": 34.39575555220132,
    "nsar": 0.4826963531024329,
    "theta_u": 115.60218755144177,
    "theta_d": 90.57872556560777,
    "fall_detected": true
  },
  {
    "trunk_angle": null,
    "nsar": null,
    "theta_u": null,
    "theta_d": null,
    "fall_detected": false
  },
  {
    "trunk_angle": null,
    "nsar": null,
    "theta_u": null,
    "theta_d": null,
    "fall_detected": false
  },
  {
    "trunk_angle": 34.200952894492765,
    "nsar": 0.9568342841369157,
    "theta_u": 126.34745820888527,
    "theta_d": 52.81529354676688,
    "fall_detected": true
  },
  {
    "trunk_angle": 35.069799682517726,
    "nsar": 1.2388855661881977,
    "theta_u": 120.46554491945989,
    "theta_d": 80.0493733120484,
    "fall_detected": true
  },
  {
    "trunk_angle": null,
    "nsar": null,
    "theta_u": null,
    "theta_d": null,
    "fall_detected": false
  },
  {
    "trunk_angle": null,
    "nsar": null,
    "theta_u": null,
    "theta_d": null,
    "fall_detected": false
  },
  {
    "trunk_angle": null,
    "nsar": null,
    "theta_u": null,
    "theta_d": null,
    "fall_detected": false
  },
  {
    "trunk_angle": null,
    "nsar": null,
    "theta_u": null,
    "theta_d": null,
    "fall_detected": false
  },
  {
    "trunk_angle": null,
    "nsar": null,
    "theta_u": null,
    "theta_d": null,
    "fall_detected": false
  },
  {
    "trunk_angle": null,
    "nsar": null,
    "theta_u": null,
    "theta_d": null,
    "fall_detected": false
  },
  {
    "trunk_angle": null,
    "nsar": null,
    "theta_u": null,
    "theta_d": null,
    "fall_detected": false
  },
  {
    "trunk_angle": null,
    "nsar": null,
    "theta_u": null,
    "theta_d": null,
    "fall_detected": false
  },
  {
    "trunk_angle": null,
    "nsar": null,
    "theta_u": null,
    "theta_d": null,
    "fall_detected": false
  },
  {
    "trunk_angle": null,
    "nsar": null,
    "theta_u": null,
    "theta_d": null,
    "fall_detected": false
  },
  {
    "trunk_angle": null,
    "nsar": null,
    "theta_u": null,
    "theta_d": null,
    "fall_detected": false
  },
  {
    "trunk_angle": null,
    "nsar": null,
    "theta_u": null,
    "theta_d": null,
    "fall_detected": false
  },
  {
    "trunk_angle": null,
    "nsar": null,
    "theta_u": null,
    "theta_d": null,
    "fall_detected": false
  },
  {
    "trunk_angle": null,
    "nsar": null,
    "theta_u": null,
    "theta_d": null,
    "fall_detected": false
  },
  {
    "trunk_angle": null,
    "nsar": null,
    "theta_u": null,
    "theta_d": null,
    "fall_detected": false
  },
  {
    "trunk_angle": null,
    "nsar": null,
    "theta_u": null,
    "theta_d": null,
    "fall_detected": false
  },
  {
    "trunk_angle": null,
    "nsar": null,
    "theta_u": null,
    "theta_d": null,
    "fall_detected": false
  },
  {
    "trunk_angle": null,
    "nsar": null,
    "theta_u": null,
    "theta_d": null,
    "fall_detected": false
  },
  {
    "trunk_angle": null,
    "nsar": null,
    "theta_u": null,
    "theta_d": null,
    "fall_detected": false
  },
  {
    "trunk_angle": null,
    "nsar": null,
    "theta_u": null,
    "theta_d": null,
    "fall_detected": false
  },
  {
    "trunk_angle": null,
    "nsar": null,
    "theta_u": null,
    "theta_d": null,
    "fall_detected": false
  },
  {
    "trunk_angle": null,
    "nsar": null,
    "theta_u": null,
    "theta_d": null,
    "fall_detected": false
  },
  {
    "trunk_angle": null,
    "nsar": null,
    "theta_u": null,
    "theta_d": null,
    "fall_detected": false
  },
  {
    "trunk_angle": null,
    "nsar": null,
    "theta_u": null,
    "theta_d": null,
    "fall_detected": false
  },
  {
    "trunk_angle": null,
    "nsar": null,
    "theta_u": null,
    "theta_d": null,
    "fall_detected": false
  },
  {
    "trunk_angle": null,
    "nsar": null,
    "theta_u": null,
    "theta_d": null,
    "fall_detected": false
  },
  {
    "trunk_angle": null,
    "nsar": null,
    "theta_u": null,
    "theta_d": null,
    "fall_detected": false
  },
  {
    "trunk_angle": null,
    "nsar": null,
    "theta_u": null,
    "theta_d": null,
    "fall_detected": false
  },
  {
    "trunk_angle": null,
    "nsar": null,
    "theta_u": null,
    "theta_d": null,
    "fall_detected": false
  },
  {
    "trunk_angle": null,
    "nsar": null,
    "theta_u": null,
    "theta_d": null,
    "fall_detected": false
  },
  {
    "trunk_angle": null,
    "nsar": null,
    "theta_u": null,
    "theta_d": null,
    "fall_detected": false
  },
  {
    "trunk_angle": null,
    "nsar": null,
    "theta_u": null,
    "theta_d": null,
    "fall_detected": false
  },
  {
    "trunk_angle": null,
    "nsar": null,
    "theta_u": null,
    "theta_d": null,
    "fall_detected": false
  },
  {
    "trunk_angle": null,
    "nsar": null,
    "theta_u": null,
    "theta_d": null,
    "fall_detected": false
  },
  {
    "trunk_angle": null,
    "nsar": null,
    "theta_u": null,
    "theta_d": null,
    "fall_detected": false
  },
  {
    "trunk_angle": null,
    "nsar": null,
    "theta_u": null,
    "theta_d": null,
    "fall_detected": false
  },
  {
    "trunk_angle": null,
    "nsar": null,
    "theta_u": null,
    "theta_d": null,
    "fall_detected": false
  },
  {
    "trunk_angle": null,
    "nsar": null,
    "theta_u": null,
    "theta_d": null,
    "fall_detected": false
  },
  {
    "trunk_angle": null,
    "nsar": null,
    "theta_u": null,
    "theta_d": null,
    "fall_detected": false
  },
  {
    "trunk_angle": null,
    "nsar": null,
    "theta_u": null,
    "theta_d": null,
    "fall_detected": false
  },
  {
    "trunk_angle": null,
    "nsar": null,
    "theta_u": null,
    "theta_d": null,
    "fall_detected": false
  },
  {
    "trunk_angle": null,
    "nsar": null,
    "theta_u": null,
    "theta_d": null,
    "fall_detected": false
  },
  {
    "trunk_angle": null,
    "nsar": null,
    "theta_u": null,
    "theta_d": null,
    "fall_detected": false
  },
  {
    "trunk_angle": null,
    "nsar": null,
    "theta_u": null,
    "theta_d": null,
    "fall_detected": false
  },
  {
    "trunk_angle": null,
    "nsar": null,
    "theta_u": null,
    "theta_d": null,
    "fall_detected": false
  },
  {
    "trunk_angle": null,
    "nsar": null,
    "theta_u": null,
    "theta_d": null,
    "fall_detected": false
  },
  {
    "trunk_angle": null,
    "nsar": null,
    "theta_u": null,
    "theta_d": null,
    "fall_detected": false
  },
  {
    "trunk_angle": null,
    "nsar": null,
    "theta_u": null,
    "theta_d": null,
    "fall_detected": false
  },
  {
    "trunk_angle": null,
    "nsar": null,
    "theta_u": null,
    "theta_d": null,
    "fall_detected": false
  },
  {
    "trunk_angle": null,
    "nsar": null,
    "theta_u": null,
    "theta_d": null,
    "fall_detected": false
  },
  {
    "trunk_angle": null,
    "nsar": null,
    "theta_u": null,
    "theta_d": null,
    "fall_detected": false
  },
  {
    "trunk_angle": null,
    "nsar": null,
    "theta_u": null,
    "theta_d": null,
    "fall_detected": false
  },
  {
    "trunk_angle": null,
    "nsar": null,
    "theta_u": null,
    "theta_d": null,
    "fall_detected": false
  },
  {
    "trunk_angle": null,
    "nsar": null,
    "theta_u": null,
    "theta_d": null,
    "fall_detected": false
  },
  {
    "trunk_angle": null,
    "nsar": null,
    "theta_u": null,
    "theta_d": null,
    "fall_detected": false
  },
  {
    "trunk_angle": null,
    "nsar": null,
    "theta_u": null,
    "theta_d": null,
    "fall_detected": false
  },
  {
    "trunk_angle": null,
    "nsar": null,
    "theta_u": null,
    "theta_d": null,
    "fall_detected": false
  },
  {
    "trunk_angle": null,
    "nsar": null,
    "theta_u": null,
    "theta_d": null,
    "fall_detected": false
  },
  {
    "trunk_angle": null,
    "nsar": null,
    "theta_u": null,
    "theta_d": null,
    "fall_detected": false
  },
  {
    "trunk_angle": null,
    "nsar": null,
    "theta_u": null,
    "theta_d": null,
    "fall_detected": false
  },
  {
    "trunk_angle": null,
    "nsar": null,
    "theta_u": null,
    "theta_d": null,
    "fall_detected": false
  },
  {
    "trunk_angle": null,
    "nsar": null,
    "theta_u": null,
    "theta_d": null,
    "fall_detected": false
  },
  {
    "trunk_angle": null,
    "nsar": null,
    "theta_u": null,
    "theta_d": null,
    "fall_detected": false
  },
  {
    "trunk_angle": null,
    "nsar": null,
    "theta_u": null,
    "theta_d": null,
    "fall_detected": false
  },
  {
    "trunk_angle": null,
    "nsar": null,
    "theta_u": null,
    "theta_d": null,
    "fall_detected": false
  },
  {
    "trunk_angle": null,
    "nsar": null,
    "theta_u": null,
    "theta_d": null,
    "fall_detected": false
  },
  {
    "trunk_angle": null,
    "nsar": null,
    "theta_u": null,
    "theta_d": null,
    "fall_detected": false
  }
]